securelock/__init__.py
securelock/secure_lock.py
securelock-1.0.1.dist-info/LICENSE.txt
securelock-1.0.1.dist-info/METADATA
securelock-1.0.1.dist-info/WHEEL
securelock-1.0.1.dist-info/top_level.txt
securelock-1.0.1.dist-info/RECORD
