Metadata-Version: 2.1
Name: securelock
Version: 1.0.1
Summary: A simple library for secure text encryption and decryption using salted password-based encryption.
Author-email: Umit Tasdelen <umittadelen1277@gmail.com>
License: MIT License
Project-URL: Homepage, https://github.com/umittadelen/securelock
Project-URL: Documentation, https://github.com/umittadelen/securelock#readme
Project-URL: Bug Tracker, https://github.com/umittadelen/securelock/issues
Keywords: encryption,decryption,security,password-protection
Classifier: Programming Language :: Python :: 3
Classifier: License :: OSI Approved :: MIT License
Classifier: Operating System :: OS Independent
Classifier: Topic :: Security :: Cryptography
Requires-Python: >=3.7
License-File: LICENSE.txt
